{
"pages": [
{
"id": "2-player-games-kids-kitchen",
"title": "2 Player Games Kids Kitchen",
"iframe": "https://html5.gamedistribution.com/b7ff5d7f28b2428e8b80a1e318a15efa/",
"description": ""
},
{
"id": "2-player-battle",
"title": "2 Player Battle",
"iframe": "https://html5.gamedistribution.com/4625c660923c42b8a5c8e4d2fbdc98ee/",
"description": ""
},
{
"id": "helicopter-battle-steve-2-player",
"title": "Helicopter Battle Steve 2 Player",
"iframe": "https://html5.gamedistribution.com/db903c04abc24de3b61cc1983dea4486/",
"description": ""
},
{
"id": "fnf-2-player",
"title": "FNF 2 Player",
"iframe": "https://html5.gamedistribution.com/151e89092f5a441088efc3f2e6c07e3e/",
"description": ""
},
{
"id": "2-player-online-chess",
"title": "2 Player Online Chess",
"iframe": "https://html5.gamedistribution.com/6c943823fcb94f53a8a0c51f796736aa/",
"description": ""
},
{
"id": "2-player-mini-challenge",
"title": "2 Player Mini Challenge",
"iframe": "https://html5.gamedistribution.com/a2564c29f9444f44a44b897bb5151f8e/",
"description": ""
},
{
"id": "ragdoll-arena-2-player",
"title": "Ragdoll Arena 2 Player",
"iframe": "https://html5.gamedistribution.com/bd606a10da914c5a89150d427d7ac8b7/",
"description": ""
},
{
"id": "break-bricks-2-player",
"title": "Break Bricks 2 Player",
"iframe": "https://html5.gamedistribution.com/45c618f2716645959f118801d00539b4/",
"description": ""
},
{
"id": "trial-2-player-moto-racing",
"title": "Trial 2 Player Moto Racing",
"iframe": "https://html5.gamedistribution.com/a423303dc75f407a89c0d4b84e1bb098/",
"description": ""
},
{
"id": "crazy-2-player-moto-racing",
"title": "Crazy 2 Player Moto Racing",
"iframe": "https://html5.gamedistribution.com/a3aa13bec4934ed39db9e3b7cbede84e/",
"description": ""
},
{
"id": "mouse-2-player-moto-racing",
"title": "Mouse 2 Player Moto Racing",
"iframe": "https://html5.gamedistribution.com/ade9b0d92ca34283a92b257ac80a5bc4/",
"description": ""
},
{
"id": "2-player-dark-racing",
"title": "2 Player Dark Racing",
"iframe": "https://html5.gamedistribution.com/b16baebfbdf940bea578f31855d793c5/",
"description": ""
},
{
"id": "2-player-3d-city-racer",
"title": "2 Player 3D City Racer",
"iframe": "https://html5.gamedistribution.com/2dd60c2625b440a5832405d4622af98d/",
"description": ""
},
{
"id": "2-player-battle-car-racing",
"title": "2 Player Battle Car Racing",
"iframe": "https://html5.gamedistribution.com/61b7b8e7e9414c80997a2e72190407d2/",
"description": ""
},
{
"id": "2-player-police-racing",
"title": "2 Player Police Racing",
"iframe": "https://html5.gamedistribution.com/31757e672a8e4b2dbcd4fd6d93610023/",
"description": ""
},
{
"id": "2-player-moto-racing",
"title": "2 Player Moto Racing",
"iframe": "https://html5.gamedistribution.com/59dfc35fbb794d02b18413ff129285db/",
"description": ""
},
{
"id": "2-player-red-blue-pirates",
"title": "2 Player Red Blue Pirates",
"iframe": "https://html5.gamedistribution.com/75c92df4f8114fbb9f2251c0fa71e164/",
"description": ""
},
{
"id": "2-player-imposter-soccer",
"title": "2 Player Imposter Soccer",
"iframe": "https://html5.gamedistribution.com/988efc7108c14675b1fcac7e10102e24/",
"description": ""
},
{
"id": "stickman-fighting-2-player",
"title": "Stickman Fighting 2 Player",
"iframe": "https://html5.gamedistribution.com/e61f3d39edb14176973383e5be036bb8/",
"description": ""
},
{
"id": "carrom-2-player",
"title": "Carrom 2 Player",
"iframe": "https://html5.gamedistribution.com/31f8ecc60fd84b90b403a11436b29879/",
"description": ""
},
{
"id": "2-player-math",
"title": "2 Player Math",
"iframe": "https://html5.gamedistribution.com/24c6e19e774a463fbd9cc098b308053a/",
"description": ""
},
{
"id": "2-player-head-basketball",
"title": "2 Player Head Basketball",
"iframe": "https://html5.gamedistribution.com/aa728fc542984ed0981900989755c49b/",
"description": ""
},
{
"id": "2-player-head-football",
"title": "2 Player Head Football",
"iframe": "https://html5.gamedistribution.com/e492074b2a1f46b09d084d1ef2713dff/",
"description": ""
},
{
"id": "2-player-head-volleyball",
"title": "2 Player Head Volleyball",
"iframe": "https://html5.gamedistribution.com/ce6574c9776543e4b7ca352bee444457/",
"description": ""
},
{
"id": "head-soccer-2-player",
"title": "Head Soccer 2 Player",
"iframe": "https://html5.gamedistribution.com/99adca365a9c436d9e5b0e87e092eba8/",
"description": ""
},
{
"id": "ragdoll-2-player",
"title": "Ragdoll 2 Player",
"iframe": "https://html5.gamedistribution.com/a2e224627fef4155a2bd2bbadd7be7f0/",
"description": ""
},
{
"id": "mind-games-for-2-player",
"title": "Mind Games for 2 Player",
"iframe": "https://html5.gamedistribution.com/c45503dd3360495188a222f8bc627c8d/",
"description": ""
}
]
}