{
"pages": [
{
"id": "magic-beauty-makeup",
"title": "Magic Beauty Makeup",
"iframe": "https://html5.gamedistribution.com/5b143b4172204a238238038e229e5cc3/",
"description": ""
},
{
"id": "asmr-makeover-makeup-studio",
"title": "ASMR Makeover & Makeup Studio",
"iframe": "https://html5.gamedistribution.com/e7cb93267da745e596429a4735ab5457/",
"description": ""
},
{
"id": "dazzling-divas-makeup",
"title": "Dazzling Divas Makeup",
"iframe": "https://html5.gamedistribution.com/f786ab18d410437f846f2fd5b72ef7b6/",
"description": ""
},
{
"id": "sweet-and-fruity-makeup",
"title": "Sweet And Fruity Makeup",
"iframe": "https://html5.gamedistribution.com/d8c6283bc0e6487681f237dca7dd6b89/",
"description": ""
},
{
"id": "graduation-makeup-trends",
"title": "Graduation Makeup Trends",
"iframe": "https://html5.gamedistribution.com/761169e0288b433f8f8ddcd27da627e5/",
"description": ""
},
{
"id": "makeup-fruits",
"title": "Makeup Fruits",
"iframe": "https://html5.gamedistribution.com/42c3d8e051fd4ed191cdaef81a0ab339/",
"description": ""
},
{
"id": "monsterella-fantasy-makeup",
"title": "Monsterella Fantasy Makeup",
"iframe": "https://html5.gamedistribution.com/70535cd518e54d8e9eaa5e5b8517a7a2/",
"description": ""
},
{
"id": "makeup-trends-then-and-now",
"title": "Makeup Trends: Then And Now",
"iframe": "https://html5.gamedistribution.com/8721384cfb1442ae948119bbfaf0d467/",
"description": ""
},
{
"id": "monster-makeup-3d",
"title": "Monster Makeup 3D",
"iframe": "https://html5.gamedistribution.com/7b08e71b06aa45f4ac02a2118ad0b055/",
"description": ""
},
{
"id": "black-hole-beauty-makeup",
"title": "Black Hole: Beauty Makeup",
"iframe": "https://html5.gamedistribution.com/60832a32b0c44409961bc98128b9cbbd/",
"description": ""
},
{
"id": "mega-makeup-seasons-best",
"title": "Mega Makeup - Seasons Best",
"iframe": "https://html5.gamedistribution.com/7c05278108ea463d8c783cac41444d9d/",
"description": ""
},
{
"id": "eye-art-perfect-makeup-artist",
"title": "Eye Art Perfect Makeup Artist",
"iframe": "https://html5.gamedistribution.com/eaa53f029692415fbc6601955d659fb1/",
"description": ""
},
{
"id": "asoka-makeup-indian-bride",
"title": "Asoka Makeup Indian Bride",
"iframe": "https://html5.gamedistribution.com/18fe7e7f509e408987b9099a56765a75/",
"description": ""
},
{
"id": "mermaidcore-makeup",
"title": "Mermaidcore Makeup",
"iframe": "https://html5.gamedistribution.com/7d3336e382c443d5a27edcfd6f12ef28/",
"description": ""
},
{
"id": "festival-vibes-makeup",
"title": "Festival Vibes Makeup",
"iframe": "https://html5.gamedistribution.com/e51326a037b6482ea51f0381484aefe0/",
"description": ""
},
{
"id": "makeup-stack",
"title": "Makeup Stack",
"iframe": "https://html5.gamedistribution.com/2960e3f573b7447eadc2d65ac76ffcc5/",
"description": ""
},
{
"id": "diy-makeup-salon-spa-makeover-studio",
"title": "DIY Makeup Salon - SPA Makeover Studio",
"iframe": "https://html5.gamedistribution.com/0ce2cfae47524dceb7108cd7f69134bb/",
"description": ""
},
{
"id": "valentines-makeup-trends",
"title": "Valentines Makeup Trends",
"iframe": "https://html5.gamedistribution.com/ad83423d36c54535b3b66fd11086781e/",
"description": ""
},
{
"id": "new-year-makeup-trends",
"title": "New Year Makeup Trends",
"iframe": "https://html5.gamedistribution.com/c86498a00e2447a7a1e9080c819e5540/",
"description": ""
},
{
"id": "makeup-makeover-girl-games",
"title": "Makeup & Makeover Girl Games",
"iframe": "https://html5.gamedistribution.com/86459babe3d04990b9bff30346c7f5c0/",
"description": ""
},
{
"id": "makeup-studio-halloween",
"title": "Makeup Studio Halloween",
"iframe": "https://html5.gamedistribution.com/c2b109375d7e482cb5769babf7043164/",
"description": ""
},
{
"id": "makeup-artist-3d",
"title": "Makeup Artist 3D",
"iframe": "https://html5.gamedistribution.com/d7245e3e0ea84cc888c75a89c80f98bc/",
"description": ""
},
{
"id": "korean-supermodel-makeup",
"title": "Korean Supermodel Makeup",
"iframe": "https://html5.gamedistribution.com/4bf611e2ec024314bcf047eeae34eefc/",
"description": ""
},
{
"id": "super-doll-makeup-transform",
"title": "Super Doll Makeup Transform",
"iframe": "https://html5.gamedistribution.com/440581f1a56948e3ac4932b29928fd4d/",
"description": ""
},
{
"id": "goldie-emo-makeup",
"title": "Goldie Emo Makeup",
"iframe": "https://html5.gamedistribution.com/0eb6f93d3a0a4800a6d038270ee55d72/",
"description": ""
},
{
"id": "harley-quinn-hair-and-makeup-studio",
"title": "Harley Quinn Hair and Makeup Studio",
"iframe": "https://html5.gamedistribution.com/2af3eab6f5504627999c571e221dbd59/",
"description": ""
},
{
"id": "sisters-fashionista-makeup",
"title": "Sisters Fashionista Makeup",
"iframe": "https://html5.gamedistribution.com/2459eeb811794191b63a279e7a293006/",
"description": ""
},
{
"id": "makeup-for-a-star",
"title": "Makeup for a Star",
"iframe": "https://html5.gamedistribution.com/d5ef345947da40e998cad4abf2826c3e/",
"description": ""
},
{
"id": "ellie-coachella-makeup",
"title": "Ellie Coachella Makeup",
"iframe": "https://html5.gamedistribution.com/817c42b68ff5450486e7d854218acd49/",
"description": ""
},
{
"id": "ella-makeup-removal",
"title": "Ella Makeup Removal",
"iframe": "https://html5.gamedistribution.com/517df202e5c5478eb9c0d97278e08af7/",
"description": ""
},
{
"id": "2018-stylish-makeup-look",
"title": "2018 Stylish Makeup Look",
"iframe": "https://html5.gamedistribution.com/073097155a984c509661e7494deb2fca/",
"description": ""
},
{
"id": "kardashians-spooky-makeup",
"title": "Kardashians Spooky Makeup",
"iframe": "https://html5.gamedistribution.com/b980487fec244a48866d531ae33758c7/",
"description": ""
},
{
"id": "kitty-beach-makeup",
"title": "Kitty Beach Makeup",
"iframe": "https://html5.gamedistribution.com/9e78944237184aeebf5ad0cd82a5cea9/",
"description": ""
},
{
"id": "mermaids-makeup-salon",
"title": "Mermaids Makeup Salon",
"iframe": "https://html5.gamedistribution.com/a9e276eb3c104843ae68ec0bebb8e5dd/",
"description": ""
},
{
"id": "sery-actress-dolly-makeup",
"title": "Sery Actress Dolly Makeup",
"iframe": "https://html5.gamedistribution.com/cf12da3ecb5442f5a7504c5a8a50636e/",
"description": ""
},
{
"id": "tris-vip-dolly-makeup",
"title": "Tris VIP Dolly Makeup",
"iframe": "https://html5.gamedistribution.com/562f6000935f42ee95c45bfd7c6cfd1b/",
"description": ""
},
{
"id": "wedding-perfect-makeup",
"title": "Wedding Perfect MakeUp",
"iframe": "https://html5.gamedistribution.com/3d32c9c84291433c8bcf7363db2e9cd4/",
"description": ""
},
{
"id": "bffs-makeup-time",
"title": "BFFs Makeup Time",
"iframe": "https://html5.gamedistribution.com/7065fd502e9046db8e9188ce1762a3d6/",
"description": ""
},
{
"id": "spring-perfect-makeup",
"title": "Spring Perfect Makeup",
"iframe": "https://html5.gamedistribution.com/d29aba8cd21348198e5b3b74165c3d2a/",
"description": ""
},
{
"id": "sery-bride-dolly-makeup",
"title": "Sery Bride Dolly Makeup",
"iframe": "https://html5.gamedistribution.com/b8f5d2a0a0a242e291ebc769722669f1/",
"description": ""
},
{
"id": "birthday-party-perfect-makeup",
"title": "Birthday Party Perfect Makeup",
"iframe": "https://html5.gamedistribution.com/0ca6e8df68c94cff8ba79f3c619b0084/",
"description": ""
},
{
"id": "elsa-new-year-makeup",
"title": "Elsa New Year Makeup",
"iframe": "https://html5.gamedistribution.com/75b9cd1ce3b64732a93b46954f0fa5ed/",
"description": ""
},
{
"id": "mermaid-makeup-room",
"title": "Mermaid Makeup Room",
"iframe": "https://html5.gamedistribution.com/5778fb4aeac24ecb90668fa0a80b5e2e/",
"description": ""
}
]
}